veezi_sdk/__init__.py
veezi_sdk/veezi.py
veezi_sdk-0.1.6.dist-info/METADATA
veezi_sdk-0.1.6.dist-info/WHEEL
veezi_sdk-0.1.6.dist-info/RECORD
