Metadata-Version: 2.4
Name: veezi-sdk
Version: 0.1.6
Summary: SDK for interacting with the Veezi API
Author-email: Måns Östman <mans.ostman@gmail.com>
Requires-Python: >=3.13
Requires-Dist: pydantic>=2.10.2
Requires-Dist: requests>=2.32.3
